PyScrappy.py
alibaba.py
amazon.py
flipkart.py
image.py
imdb.py
instagram.py
linkedin.py
news.py
snapdeal.py
soundcloud.py
spotify.py
stock.py
swiggy.py
twitter.py
wikipedia.py
youtube.py
zomato.py
PyScrappy-0.1.1.dist-info/LICENSE
PyScrappy-0.1.1.dist-info/METADATA
PyScrappy-0.1.1.dist-info/WHEEL
PyScrappy-0.1.1.dist-info/top_level.txt
PyScrappy-0.1.1.dist-info/RECORD
