Metadata-Version: 2.1
Name: PyScrappy
Version: 0.1.1
Summary: Powerful web scraping tool.
Home-page: https://github.com/mldsveda/PyScrappy
Author: Vedant Tibrewal, Vedaant Singh
Author-email: mlds93363@gmail.com
License: UNKNOWN
Keywords: PyScrappy,Scraping,E-Commerce,Wikipedia,Image Scrapper,YouTube,Scrapy,Twitter,Social Media,Web Scraping,News,Stocks,Songs,Food,Instagram,Movies
Platform: UNKNOWN
Classifier: Programming Language :: Python :: 3
Classifier: License :: OSI Approved :: MIT License
Classifier: Operating System :: OS Independent
Requires-Python: >=3.6
License-File: LICENSE
Requires-Dist: selenium
Requires-Dist: webdriver-manager
Requires-Dist: beautifulsoup4
Requires-Dist: requests
Requires-Dist: pandas
